django_geoip/__init__.py
django_geoip/base.py
django_geoip/compat.py
django_geoip/middleware.py
django_geoip/models.py
django_geoip/storage.py
django_geoip/urls.py
django_geoip/utils.py
django_geoip/views.py
django_geoip/management/__init__.py
django_geoip/management/ipgeobase.py
django_geoip/management/iso3166_1.py
django_geoip/management/commands/__init__.py
django_geoip/management/commands/geoip_update.py
django_geoip/migrations/0001_initial.py
django_geoip/migrations/0002_countrynames.py
django_geoip/migrations/__init__.py
django_geoip/settings/__init__.py
django_geoip/settings/geoip_settings.py
django_geoip/settings/ipgeobase_settings.py
django_geoip/vendor/__init__.py
django_geoip/vendor/progressbar/__init__.py
django_geoip/vendor/progressbar/compat.py
django_geoip/vendor/progressbar/progressbar.py
django_geoip/vendor/progressbar/widgets.py
django_geoip-0.4.dist-info/DESCRIPTION.rst
django_geoip-0.4.dist-info/METADATA
django_geoip-0.4.dist-info/pydist.json
django_geoip-0.4.dist-info/RECORD
django_geoip-0.4.dist-info/top_level.txt
django_geoip-0.4.dist-info/WHEEL
docs/__init__.py
docs/conf.py
test_app/__init__.py
test_app/models.py
test_app/test_settings.py
test_app/urls.py
tests/__init__.py
tests/factory.py
tests/system.py
tests/test_base.py
tests/test_management.py
tests/test_middleware.py
tests/test_models.py
tests/test_storage.py
tests/test_utils.py
tests/test_views.py
