Metadata-Version: 2.0
Name: django-geoip
Version: 0.4
Summary: App to figure out where your visitors are from by their IP address.
Home-page: https://github.com/futurecolors/django-geoip
Author: Ilya Baryshev
Author-email: baryshev@gmail.com
License: MIT
Platform: UNKNOWN
Classifier: Development Status :: 5 - Production/Stable
Classifier: Framework :: Django
Classifier: Intended Audience :: Developers
Classifier: License :: OSI Approved :: MIT License
Classifier: Operating System :: OS Independent
Classifier: Programming Language :: Python
Classifier: Programming Language :: Python :: 2.6
Classifier: Programming Language :: Python :: 2.7
Classifier: Programming Language :: Python :: 3
Classifier: Programming Language :: Python :: 3.3
Requires-Dist: django-appconf (>=0.6)
Requires-Dist: requests (>=1.0.4)
